Metadata-Version: 2.1
Name: Mensajes-agiraldomolina
Version: 6.0
Summary: Un paquete para saludar y despedir
Home-page: 
Author: Alba Giraldo
Author-email: agiraldomolina@gmail.com
Classifier: Environment :: Console
Classifier: Intended Audience :: Developers
Classifier: License :: OSI Approved :: MIT License
Classifier: Operating System :: OS Independent
Classifier: Programming Language :: Python :: 3.0
Classifier: Topic :: Utilities
License-File: LICENSE
Requires-Dist: numpy (>=1.24.2)
